scraping_class/__init__.py
scraping_class/scraping_class.py
scraping_class-0.4.dist-info/METADATA
scraping_class-0.4.dist-info/WHEEL
scraping_class-0.4.dist-info/top_level.txt
scraping_class-0.4.dist-info/RECORD
