Metadata-Version: 2.1
Name: scraping-class
Version: 0.4
Summary: Webscraper for SDS2019
Home-page: https://github.com/elben10/ScrapingClass
Author: Snorre Ralund, Jakob Jul Elben, Kristian Urup Larsen
Author-email: elbenjakobjul@gmail.com
License: MIT
Platform: UNKNOWN
